odoo/addons/hr_expense_work_acceptance/README.rst
odoo/addons/hr_expense_work_acceptance/__init__.py
odoo/addons/hr_expense_work_acceptance/__manifest__.py
odoo/addons/hr_expense_work_acceptance/i18n/es.po
odoo/addons/hr_expense_work_acceptance/i18n/hr_expense_work_acceptance.pot
odoo/addons/hr_expense_work_acceptance/i18n/it.po
odoo/addons/hr_expense_work_acceptance/models/__init__.py
odoo/addons/hr_expense_work_acceptance/models/hr_expense.py
odoo/addons/hr_expense_work_acceptance/models/res_config_settings.py
odoo/addons/hr_expense_work_acceptance/models/work_acceptance.py
odoo/addons/hr_expense_work_acceptance/readme/CONFIGURE.rst
odoo/addons/hr_expense_work_acceptance/readme/CONTRIBUTORS.rst
odoo/addons/hr_expense_work_acceptance/readme/DESCRIPTION.rst
odoo/addons/hr_expense_work_acceptance/readme/USAGE.rst
odoo/addons/hr_expense_work_acceptance/security/ir.model.access.csv
odoo/addons/hr_expense_work_acceptance/security/security.xml
odoo/addons/hr_expense_work_acceptance/static/description/icon.png
odoo/addons/hr_expense_work_acceptance/static/description/index.html
odoo/addons/hr_expense_work_acceptance/tests/__init__.py
odoo/addons/hr_expense_work_acceptance/tests/test_hr_expense_work_acceptance.py
odoo/addons/hr_expense_work_acceptance/views/expense_views.xml
odoo/addons/hr_expense_work_acceptance/views/res_config_settings_views.xml
odoo/addons/hr_expense_work_acceptance/views/work_acceptance_views.xml
odoo14_addon_hr_expense_work_acceptance-14.0.1.0.1.dev10.dist-info/METADATA
odoo14_addon_hr_expense_work_acceptance-14.0.1.0.1.dev10.dist-info/WHEEL
odoo14_addon_hr_expense_work_acceptance-14.0.1.0.1.dev10.dist-info/top_level.txt
odoo14_addon_hr_expense_work_acceptance-14.0.1.0.1.dev10.dist-info/RECORD
